create_onchain_agent/cli.py
create_onchain_agent-0.9.0.dist-info/METADATA
create_onchain_agent-0.9.0.dist-info/WHEEL
create_onchain_agent-0.9.0.dist-info/entry_points.txt
create_onchain_agent-0.9.0.dist-info/RECORD
