Metadata-Version: 2.4
Name: create-onchain-agent
Version: 0.9.0
Summary: CLI to create an onchain agent project
Author-email: Carson Roscoe <carsonroscoe7@gmail.com>
License-Expression: Apache-2.0
Keywords: agent,agentkit,ai,cdp,coinbase,crypto,sdk
Requires-Python: >=3.10
Requires-Dist: click<9,>=8.1.3
Requires-Dist: copier<10,>=9.1.0
Requires-Dist: platformdirs<5,>=4.3.6
Requires-Dist: prompt-toolkit<4,>=3.0.50
Requires-Dist: questionary<3,>=2.1.0
Requires-Dist: requests<3,>=2.32.3
Requires-Dist: rich<14,>=13.3.2
